<?xml version="1.0" encoding="UTF-8"?>
<list xmlns:xsi="http://www.w3.org/2001/XMLSchema-instance" xsi:noNamespaceSchemaLocation="../../xsd/spawns.xsd">
	<spawn name="FieldOfWispers">
		<group>
			<npc id="19543" x="81407" y="226688" z="-3600" heading="27064" respawnTime="60sec" /> <!-- Invisible NPC -->
			<npc id="34481" x="81320" y="226520" z="-3590" heading="63371" respawnTime="60sec" /> <!-- Ramer -->
			<npc id="24304" x="84024" y="225448" z="-3753" heading="54364" respawnTime="60sec" /> <!-- Groz Kropiora -->
			<npc id="24305" x="83896" y="225432" z="-3762" heading="34373" respawnTime="60sec" /> <!-- Groz Krotania -->
			<npc id="24306" x="83848" y="225512" z="-3766" heading="22269" respawnTime="60sec" /> <!-- Groz Krophy -->
			<npc id="24307" x="83992" y="225608" z="-3766" heading="6258" respawnTime="60sec" /> <!-- Groz Krotany -->
			<npc id="24308" x="84120" y="225480" z="-3746" heading="57421" respawnTime="60sec" /> <!-- Water Drake -->
			<npc id="24304" x="85848" y="226840" z="-3766" heading="63512" respawnTime="60sec" /> <!-- Groz Kropiora -->
			<npc id="24305" x="85688" y="226776" z="-3766" heading="36455" respawnTime="60sec" /> <!-- Groz Krotania -->
			<npc id="24306" x="85624" y="226888" z="-3766" heading="21362" respawnTime="60sec" /> <!-- Groz Krophy -->
			<npc id="24307" x="85736" y="227000" z="-3766" heading="8290" respawnTime="60sec" /> <!-- Groz Krotany -->
			<npc id="24308" x="85544" y="227000" z="-3766" heading="32541" respawnTime="60sec" /> <!-- Water Drake -->
			<npc id="24304" x="81864" y="223848" z="-3766" heading="58124" respawnTime="60sec" /> <!-- Groz Kropiora -->
			<npc id="24305" x="81752" y="223976" z="-3766" heading="24122" respawnTime="60sec" /> <!-- Groz Krotania -->
			<npc id="24306" x="81848" y="224024" z="-3766" heading="5344" respawnTime="60sec" /> <!-- Groz Krophy -->
			<npc id="24307" x="81960" y="223992" z="-3766" heading="62866" respawnTime="60sec" /> <!-- Groz Krotany -->
			<npc id="24308" x="81976" y="223832" z="-3766" heading="50080" respawnTime="60sec" /> <!-- Water Drake -->
			<npc id="24304" x="79896" y="225080" z="-3766" heading="60442" respawnTime="60sec" /> <!-- Groz Kropiora -->
			<npc id="24305" x="79864" y="225224" z="-3766" heading="16235" respawnTime="60sec" /> <!-- Groz Krotania -->
			<npc id="24306" x="79976" y="225256" z="-3766" heading="3385" respawnTime="60sec" /> <!-- Groz Krophy -->
			<npc id="24307" x="80104" y="225256" z="-3766" heading="65283" respawnTime="60sec" /> <!-- Groz Krotany -->
			<npc id="24308" x="80136" y="225080" z="-3766" heading="50681" respawnTime="60sec" /> <!-- Water Drake -->
			<npc id="24304" x="80456" y="222312" z="-3766" heading="52902" respawnTime="60sec" /> <!-- Groz Kropiora -->
			<npc id="24305" x="80328" y="222360" z="-3766" heading="29078" respawnTime="60sec" /> <!-- Groz Krotania -->
			<npc id="24306" x="80312" y="222552" z="-3761" heading="19231" respawnTime="60sec" /> <!-- Groz Krophy -->
			<npc id="24307" x="80488" y="222584" z="-3754" heading="1859" respawnTime="60sec" /> <!-- Groz Krotany -->
			<npc id="24308" x="80568" y="222376" z="-3766" heading="52766" respawnTime="60sec" /> <!-- Water Drake -->
			<npc id="24304" x="82232" y="221400" z="-3766" heading="57586" respawnTime="60sec" /> <!-- Groz Kropiora -->
			<npc id="24305" x="82088" y="221480" z="-3766" heading="27288" respawnTime="60sec" /> <!-- Groz Krotania -->
			<npc id="24306" x="82136" y="221576" z="-3766" heading="11466" respawnTime="60sec" /> <!-- Groz Krophy -->
			<npc id="24307" x="82280" y="221608" z="-3766" heading="2465" respawnTime="60sec" /> <!-- Groz Krotany -->
			<npc id="24308" x="82376" y="221464" z="-3766" heading="55111" respawnTime="60sec" /> <!-- Water Drake -->
			<npc id="24304" x="78088" y="219720" z="-3605" heading="11988" respawnTime="60sec" /> <!-- Groz Kropiora -->
			<npc id="24305" x="78280" y="219848" z="-3612" heading="53531" respawnTime="60sec" /> <!-- Groz Krotania -->
			<npc id="24306" x="78296" y="219704" z="-3631" heading="50681" respawnTime="60sec" /> <!-- Groz Krophy -->
			<npc id="24307" x="78136" y="219608" z="-3625" heading="43357" respawnTime="60sec" /> <!-- Groz Krotany -->
			<npc id="24308" x="78360" y="219592" z="-3646" heading="65062" respawnTime="60sec" /> <!-- Water Drake -->
			<npc id="24304" x="80616" y="219480" z="-3766" heading="62647" respawnTime="60sec" /> <!-- Groz Kropiora -->
			<npc id="24305" x="80456" y="219368" z="-3766" heading="35048" respawnTime="60sec" /> <!-- Groz Krotania -->
			<npc id="24306" x="80392" y="219544" z="-3766" heading="19668" respawnTime="60sec" /> <!-- Groz Krophy -->
			<npc id="24307" x="80600" y="219593" z="-3766" heading="2581" respawnTime="60sec" /> <!-- Groz Krotany -->
			<npc id="24308" x="80440" y="219608" z="-3766" heading="32671" respawnTime="60sec" /> <!-- Water Drake -->
			<npc id="24304" x="78904" y="217800" z="-3671" heading="51286" respawnTime="60sec" /> <!-- Groz Kropiora -->
			<npc id="24305" x="78840" y="217864" z="-3676" heading="23601" respawnTime="60sec" /> <!-- Groz Krotania -->
			<npc id="24306" x="78904" y="217912" z="-3695" heading="8098" respawnTime="60sec" /> <!-- Groz Krophy -->
			<npc id="24307" x="79032" y="217864" z="-3687" heading="61642" respawnTime="60sec" /> <!-- Groz Krotany -->
			<npc id="24308" x="79080" y="217720" z="-3656" heading="52549" respawnTime="60sec" /> <!-- Water Drake -->
			<npc id="24304" x="76680" y="219480" z="-3621" heading="27954" respawnTime="60sec" /> <!-- Groz Kropiora -->
			<npc id="24305" x="76776" y="219512" z="-3626" heading="1360" respawnTime="60sec" /> <!-- Groz Krotania -->
			<npc id="24306" x="76840" y="219368" z="-3647" heading="53299" respawnTime="60sec" /> <!-- Groz Krophy -->
			<npc id="24307" x="76744" y="219288" z="-3646" heading="39655" respawnTime="60sec" /> <!-- Groz Krotany -->
			<npc id="24308" x="76600" y="219320" z="-3623" heading="31021" respawnTime="60sec" /> <!-- Water Drake -->
			<npc id="24304" x="80760" y="217144" z="-3674" heading="55193" respawnTime="60sec" /> <!-- Groz Kropiora -->
			<npc id="24305" x="80664" y="217256" z="-3671" heading="24865" respawnTime="60sec" /> <!-- Groz Krotania -->
			<npc id="24306" x="80728" y="217320" z="-3685" heading="7866" respawnTime="60sec" /> <!-- Groz Krophy -->
			<npc id="24307" x="80856" y="217320" z="-3695" heading="407" respawnTime="60sec" /> <!-- Groz Krotany -->
			<npc id="24308" x="80936" y="217224" z="-3689" heading="56365" respawnTime="60sec" /> <!-- Water Drake -->
			<npc id="24304" x="81880" y="214872" z="-3766" heading="27243" respawnTime="60sec" /> <!-- Groz Kropiora -->
			<npc id="24305" x="82040" y="214840" z="-3766" heading="63618" respawnTime="60sec" /> <!-- Groz Krotania -->
			<npc id="24306" x="82072" y="214712" z="-3766" heading="51707" respawnTime="60sec" /> <!-- Groz Krophy -->
			<npc id="24307" x="81896" y="214648" z="-3766" heading="36471" respawnTime="60sec" /> <!-- Groz Krotany -->
			<npc id="24308" x="81704" y="214776" z="-3766" heading="34435" respawnTime="60sec" /> <!-- Water Drake -->
			<npc id="24304" x="81032" y="213000" z="-3652" heading="40399" respawnTime="60sec" /> <!-- Groz Kropiora -->
			<npc id="24305" x="81144" y="213064" z="-3660" heading="6469" respawnTime="60sec" /> <!-- Groz Krotania -->
			<npc id="24306" x="81272" y="212968" z="-3662" heading="58428" respawnTime="60sec" /> <!-- Groz Krophy -->
			<npc id="24307" x="81160" y="212824" z="-3661" heading="41890" respawnTime="60sec" /> <!-- Groz Krotany -->
			<npc id="24308" x="81000" y="212840" z="-3650" heading="31927" respawnTime="60sec" /> <!-- Water Drake -->
			<npc id="24304" x="85032" y="212520" z="-3688" heading="57265" respawnTime="60sec" /> <!-- Groz Kropiora -->
			<npc id="24305" x="84840" y="212600" z="-3672" heading="28630" respawnTime="60sec" /> <!-- Groz Krotania -->
			<npc id="24306" x="84840" y="212728" z="-3660" heading="16552" respawnTime="60sec" /> <!-- Groz Krophy -->
			<npc id="24307" x="84952" y="212760" z="-3663" heading="2280" respawnTime="60sec" /> <!-- Groz Krotany -->
			<npc id="24308" x="85112" y="212664" z="-3684" heading="60003" respawnTime="60sec" /> <!-- Water Drake -->
			<npc id="24304" x="83032" y="211848" z="-3544" heading="29307" respawnTime="60sec" /> <!-- Groz Kropiora -->
			<npc id="24305" x="83064" y="211992" z="-3556" heading="11606" respawnTime="60sec" /> <!-- Groz Krotania -->
			<npc id="24306" x="83176" y="211960" z="-3558" heading="62684" respawnTime="60sec" /> <!-- Groz Krophy -->
			<npc id="24307" x="83288" y="211864" z="-3559" heading="57859" respawnTime="60sec" /> <!-- Groz Krotany -->
			<npc id="24308" x="83176" y="211736" z="-3543" heading="41637" respawnTime="60sec" /> <!-- Water Drake -->
			<npc id="24304" x="80552" y="210360" z="-3766" heading="41041" respawnTime="60sec" /> <!-- Groz Kropiora -->
			<npc id="24305" x="80600" y="210600" z="-3766" heading="14430" respawnTime="60sec" /> <!-- Groz Krotania -->
			<npc id="24306" x="80744" y="210616" z="-3766" heading="1981" respawnTime="60sec" /> <!-- Groz Krophy -->
			<npc id="24307" x="80792" y="210488" z="-3766" heading="52976" respawnTime="60sec" /> <!-- Groz Krotany -->
			<npc id="24308" x="80728" y="210312" z="-3766" heading="45423" respawnTime="60sec" /> <!-- Water Drake -->
			<npc id="24304" x="78248" y="211976" z="-3694" heading="29585" respawnTime="60sec" /> <!-- Groz Kropiora -->
			<npc id="24305" x="78360" y="212024" z="-3690" heading="4117" respawnTime="60sec" /> <!-- Groz Krotania -->
			<npc id="24306" x="78488" y="211880" z="-3682" heading="57479" respawnTime="60sec" /> <!-- Groz Krophy -->
			<npc id="24307" x="78392" y="211784" z="-3687" heading="40751" respawnTime="60sec" /> <!-- Groz Krotany -->
			<npc id="24308" x="78152" y="211880" z="-3699" heading="28912" respawnTime="60sec" /> <!-- Water Drake -->
			<npc id="24304" x="76648" y="213368" z="-3766" heading="26923" respawnTime="60sec" /> <!-- Groz Kropiora -->
			<npc id="24305" x="76760" y="213384" z="-3766" heading="1612" respawnTime="60sec" /> <!-- Groz Krotania -->
			<npc id="24306" x="76904" y="213272" z="-3766" heading="58623" respawnTime="60sec" /> <!-- Groz Krophy -->
			<npc id="24307" x="76840" y="213176" z="-3766" heading="42944" respawnTime="60sec" /> <!-- Groz Krotany -->
			<npc id="24308" x="76616" y="213160" z="-3766" heading="33579" respawnTime="60sec" /> <!-- Water Drake -->
			<npc id="24304" x="77384" y="215400" z="-3766" heading="23231" respawnTime="60sec" /> <!-- Groz Kropiora -->
			<npc id="24305" x="77560" y="215400" z="-3766" heading="64270" respawnTime="60sec" /> <!-- Groz Krotania -->
			<npc id="24306" x="77624" y="215288" z="-3766" heading="54677" respawnTime="60sec" /> <!-- Groz Krophy -->
			<npc id="24307" x="77560" y="215192" z="-3766" heading="43043" respawnTime="60sec" /> <!-- Groz Krotany -->
			<npc id="24308" x="77384" y="215208" z="-3766" heading="31750" respawnTime="60sec" /> <!-- Water Drake -->
			<npc id="24304" x="79208" y="215000" z="-3692" heading="19235" respawnTime="60sec" /> <!-- Groz Kropiora -->
			<npc id="24305" x="79320" y="215000" z="-3690" heading="186" respawnTime="60sec" /> <!-- Groz Krotania -->
			<npc id="24306" x="79416" y="214872" z="-3672" heading="55900" respawnTime="60sec" /> <!-- Groz Krophy -->
			<npc id="24307" x="79352" y="214776" z="-3668" heading="42805" respawnTime="60sec" /> <!-- Groz Krotany -->
			<npc id="24308" x="79176" y="214808" z="-3681" heading="31171" respawnTime="60sec" /> <!-- Water Drake -->
			<npc id="24304" x="77320" y="208776" z="-3465" heading="36819" respawnTime="60sec" /> <!-- Groz Kropiora -->
			<npc id="24305" x="77272" y="208632" z="-3457" heading="45880" respawnTime="60sec" /> <!-- Groz Krotania -->
			<npc id="24306" x="77368" y="208632" z="-3488" heading="65342" respawnTime="60sec" /> <!-- Groz Krophy -->
			<npc id="24307" x="77480" y="208712" z="-3524" heading="4635" respawnTime="60sec" /> <!-- Groz Krotany -->
			<npc id="24308" x="77384" y="208872" z="-3484" heading="47559" respawnTime="60sec" /> <!-- Water Drake -->
			<npc id="24304" x="77736" y="206472" z="-3506" heading="46288" respawnTime="60sec" /> <!-- Groz Kropiora -->
			<npc id="24305" x="77720" y="206632" z="-3529" heading="18244" respawnTime="60sec" /> <!-- Groz Krotania -->
			<npc id="24306" x="77880" y="206680" z="-3546" heading="3550" respawnTime="60sec" /> <!-- Groz Krophy -->
			<npc id="24307" x="77960" y="206568" z="-3528" heading="55438" respawnTime="60sec" /> <!-- Groz Krotany -->
			<npc id="24308" x="77912" y="206440" z="-3503" heading="44695" respawnTime="60sec" /> <!-- Water Drake -->
			<npc id="24304" x="81224" y="206600" z="-3693" heading="56277" respawnTime="60sec" /> <!-- Groz Kropiora -->
			<npc id="24305" x="81128" y="206568" z="-3700" heading="35599" respawnTime="60sec" /> <!-- Groz Krotania -->
			<npc id="24306" x="81032" y="206632" z="-3701" heading="26019" respawnTime="60sec" /> <!-- Groz Krophy -->
			<npc id="24307" x="81048" y="206760" z="-3698" heading="15097" respawnTime="60sec" /> <!-- Groz Krotany -->
			<npc id="24308" x="81208" y="206776" z="-3691" heading="1188" respawnTime="60sec" /> <!-- Water Drake -->
			<npc id="24304" x="79048" y="204600" z="-3734" heading="5110" respawnTime="60sec" /> <!-- Groz Kropiora -->
			<npc id="24305" x="78872" y="204648" z="-3761" heading="34271" respawnTime="60sec" /> <!-- Groz Krotania -->
			<npc id="24306" x="79021" y="204826" z="-3766" heading="9178" respawnTime="60sec" /> <!-- Groz Krophy -->
			<npc id="24307" x="79272" y="204808" z="-3766" heading="63719" respawnTime="60sec" /> <!-- Groz Krotany -->
			<npc id="24308" x="79224" y="204552" z="-3715" heading="43018" respawnTime="60sec" /> <!-- Water Drake -->
			<npc id="24304" x="81416" y="204360" z="-3640" heading="63813" respawnTime="60sec" /> <!-- Groz Kropiora -->
			<npc id="24305" x="81352" y="204264" z="-3650" heading="45077" respawnTime="60sec" /> <!-- Groz Krotania -->
			<npc id="24306" x="81176" y="204328" z="-3659" heading="29554" respawnTime="60sec" /> <!-- Groz Krophy -->
			<npc id="24307" x="81176" y="204440" z="-3655" heading="16194" respawnTime="60sec" /> <!-- Groz Krotany -->
			<npc id="24308" x="81320" y="204552" z="-3642" heading="6984" respawnTime="60sec" /> <!-- Water Drake -->
			<npc id="24304" x="83960" y="203176" z="-3579" heading="7725" respawnTime="60sec" /> <!-- Groz Kropiora -->
			<npc id="24305" x="83832" y="203208" z="-3573" heading="30858" respawnTime="60sec" /> <!-- Groz Krotania -->
			<npc id="24307" x="83784" y="203320" z="-3579" heading="20261" respawnTime="60sec" /> <!-- Groz Krotany -->
			<npc id="24306" x="83864" y="203384" z="-3585" heading="7348" respawnTime="60sec" /> <!-- Groz Krophy -->
			<npc id="24308" x="84024" y="203320" z="-3592" heading="61815" respawnTime="60sec" /> <!-- Water Drake -->
			<npc id="24304" x="84408" y="200696" z="-3672" heading="40777" respawnTime="60sec" /> <!-- Groz Kropiora -->
			<npc id="24305" x="84392" y="200808" z="-3682" heading="17558" respawnTime="60sec" /> <!-- Groz Krotania -->
			<npc id="24306" x="84488" y="200888" z="-3698" heading="7348" respawnTime="60sec" /> <!-- Groz Krophy -->
			<npc id="24307" x="84584" y="200824" z="-3689" heading="59066" respawnTime="60sec" /> <!-- Groz Krotany -->
			<npc id="24308" x="84584" y="200664" z="-3677" heading="48643" respawnTime="60sec" /> <!-- Water Drake -->
			<npc id="24304" x="83928" y="204840" z="-3522" heading="7182" respawnTime="60sec" /> <!-- Groz Kropiora -->
			<npc id="24305" x="83864" y="204744" z="-3514" heading="44618" respawnTime="60sec" /> <!-- Groz Krotania -->
			<npc id="24306" x="83800" y="204776" z="-3527" heading="27319" respawnTime="60sec" /> <!-- Groz Krophy -->
			<npc id="24307" x="83784" y="204920" z="-3545" heading="17147" respawnTime="60sec" /> <!-- Groz Krotany -->
			<npc id="24308" x="83720" y="204840" z="-3542" heading="42189" respawnTime="60sec" /> <!-- Water Drake -->
			<npc id="24304" x="85944" y="202744" z="-3690" heading="57664" respawnTime="60sec" /> <!-- Groz Kropiora -->
			<npc id="24305" x="85896" y="202600" z="-3690" heading="45337" respawnTime="60sec" /> <!-- Groz Krotania -->
			<npc id="24306" x="86104" y="202584" z="-3694" heading="20696" respawnTime="60sec" /> <!-- Groz Krophy -->
			<npc id="24307" x="85960" y="202472" z="-3691" heading="39866" respawnTime="60sec" /> <!-- Groz Krotany -->
			<npc id="24308" x="85816" y="202456" z="-3692" heading="33922" respawnTime="60sec" /> <!-- Water Drake -->
			<npc id="24304" x="86920" y="204328" z="-3690" heading="19262" respawnTime="60sec" /> <!-- Groz Kropiora -->
			<npc id="24305" x="86824" y="204504" z="-3698" heading="21895" respawnTime="60sec" /> <!-- Groz Krotania -->
			<npc id="24306" x="86776" y="204392" z="-3706" heading="45949" respawnTime="60sec" /> <!-- Groz Krophy -->
			<npc id="24307" x="86840" y="204232" z="-3702" heading="52649" respawnTime="60sec" /> <!-- Groz Krotany -->
			<npc id="24308" x="87064" y="204344" z="-3694" heading="5081" respawnTime="60sec" /> <!-- Water Drake -->
			<npc id="24304" x="86440" y="206866" z="-3680" heading="16227" respawnTime="60sec" /> <!-- Groz Kropiora -->
			<npc id="24305" x="86319" y="207077" z="-3667" heading="29481" respawnTime="60sec" /> <!-- Groz Krotania -->
			<npc id="24306" x="86296" y="206920" z="-3669" heading="45059" respawnTime="60sec" /> <!-- Groz Krophy -->
			<npc id="24307" x="86264" y="206744" z="-3677" heading="45306" respawnTime="60sec" /> <!-- Groz Krotany -->
			<npc id="24308" x="86088" y="207000" z="-3665" heading="22865" respawnTime="60sec" /> <!-- Water Drake -->
			<npc id="24304" x="84056" y="207720" z="-3708" heading="53277" respawnTime="60sec" /> <!-- Groz Kropiora -->
			<npc id="24305" x="84216" y="207544" z="-3703" heading="60286" respawnTime="60sec" /> <!-- Groz Krotania -->
			<npc id="24307" x="84312" y="207608" z="-3697" heading="5725" respawnTime="60sec" /> <!-- Groz Krotany -->
			<npc id="24306" x="84344" y="207816" z="-3697" heading="17776" respawnTime="60sec" /> <!-- Groz Krophy -->
			<npc id="24308" x="84440" y="207704" z="-3692" heading="56110" respawnTime="60sec" /> <!-- Water Drake -->
			<npc id="24304" x="86456" y="210136" z="-3695" heading="10055" respawnTime="60sec" /> <!-- Groz Kropiora -->
			<npc id="24305" x="86456" y="210248" z="-3689" heading="16632" respawnTime="60sec" /> <!-- Groz Krotania -->
			<npc id="24306" x="86312" y="210280" z="-3693" heading="36959" respawnTime="60sec" /> <!-- Groz Krophy -->
			<npc id="24307" x="86264" y="210136" z="-3713" heading="46249" respawnTime="60sec" /> <!-- Groz Krotany -->
			<npc id="24308" x="86456" y="209992" z="-3705" heading="58095" respawnTime="60sec" /> <!-- Water Drake -->
			<npc id="24304" x="88584" y="208616" z="-3682" heading="10645" respawnTime="60sec" /> <!-- Groz Kropiora -->
			<npc id="24305" x="88696" y="208552" z="-3677" heading="56870" respawnTime="60sec" /> <!-- Groz Krotania -->
			<npc id="24306" x="88760" y="208696" z="-3664" heading="12525" respawnTime="60sec" /> <!-- Groz Krophy -->
			<npc id="24307" x="88648" y="208840" z="-3677" heading="23298" respawnTime="60sec" /> <!-- Groz Krotany -->
			<npc id="24308" x="88488" y="208744" z="-3709" heading="38268" respawnTime="60sec" /> <!-- Water Drake -->
			<npc id="24304" x="87432" y="213960" z="-3576" heading="20596" respawnTime="60sec" /> <!-- Groz Kropiora -->
			<npc id="24305" x="87432" y="214120" z="-3594" heading="16633" respawnTime="60sec" /> <!-- Groz Krotania -->
			<npc id="24306" x="87608" y="214072" z="-3586" heading="63145" respawnTime="60sec" /> <!-- Groz Krophy -->
			<npc id="24307" x="87736" y="213880" z="-3565" heading="43378" respawnTime="60sec" /> <!-- Groz Krotany -->
			<npc id="24308" x="87464" y="213816" z="-3551" heading="61485" respawnTime="60sec" /> <!-- Water Drake -->
			<npc id="24304" x="94344" y="219256" z="-3697" heading="29372" respawnTime="60sec" /> <!-- Groz Kropiora -->
			<npc id="24305" x="94296" y="219160" z="-3703" heading="44405" respawnTime="60sec" /> <!-- Groz Krotania -->
			<npc id="24306" x="94344" y="219080" z="-3710" heading="55595" respawnTime="60sec" /> <!-- Groz Krophy -->
			<npc id="24307" x="94504" y="219080" z="-3723" heading="667" respawnTime="60sec" /> <!-- Groz Krotany -->
			<npc id="24308" x="94520" y="219240" z="-3728" heading="14847" respawnTime="60sec" /> <!-- Water Drake -->
			<npc id="24304" x="94232" y="216856" z="-3683" heading="42010" respawnTime="60sec" /> <!-- Groz Kropiora -->
			<npc id="24305" x="94232" y="217048" z="-3704" heading="16383" respawnTime="60sec" /> <!-- Groz Krotania -->
			<npc id="24306" x="94328" y="217032" z="-3720" heading="63641" respawnTime="60sec" /> <!-- Groz Krophy -->
			<npc id="24307" x="94376" y="216840" z="-3720" heading="51733" respawnTime="60sec" /> <!-- Groz Krotany -->
			<npc id="24308" x="94152" y="216712" z="-3659" heading="28100" respawnTime="60sec" /> <!-- Water Drake -->
			<npc id="24304" x="92840" y="214232" z="-3626" heading="675" respawnTime="60sec" /> <!-- Groz Kropiora -->
			<npc id="24305" x="92920" y="214360" z="-3638" heading="9777" respawnTime="60sec" /> <!-- Groz Krotania -->
			<npc id="24306" x="93016" y="214280" z="-3644" heading="58722" respawnTime="60sec" /> <!-- Groz Krophy -->
			<npc id="24307" x="93064" y="214152" z="-3646" heading="52903" respawnTime="60sec" /> <!-- Groz Krotany -->
			<npc id="24308" x="92856" y="214088" z="-3624" heading="27423" respawnTime="60sec" /> <!-- Water Drake -->
			<npc id="24304" x="91784" y="211640" z="-3718" heading="40295" respawnTime="60sec" /> <!-- Groz Kropiora -->
			<npc id="24305" x="91768" y="211784" z="-3725" heading="19317" respawnTime="60sec" /> <!-- Groz Krotania -->
			<npc id="24306" x="91864" y="211768" z="-3750" heading="63058" respawnTime="60sec" /> <!-- Groz Krophy -->
			<npc id="24307" x="91960" y="211624" z="-3752" heading="55038" respawnTime="60sec" /> <!-- Groz Krotany -->
			<npc id="24308" x="91896" y="211496" z="-3718" heading="44084" respawnTime="60sec" /> <!-- Water Drake -->
			<npc id="24304" x="90136" y="214584" z="-3716" heading="23982" respawnTime="60sec" /> <!-- Groz Kropiora -->
			<npc id="24305" x="90056" y="214504" z="-3708" heading="41238" respawnTime="60sec" /> <!-- Groz Krotania -->
			<npc id="24306" x="90104" y="214408" z="-3708" heading="53946" respawnTime="60sec" /> <!-- Groz Krophy -->
			<npc id="24307" x="90216" y="214344" z="-3708" heading="60163" respawnTime="60sec" /> <!-- Groz Krotany -->
			<npc id="24308" x="90328" y="214392" z="-3716" heading="3886" respawnTime="60sec" /> <!-- Water Drake -->
			<npc id="24304" x="90360" y="216632" z="-3682" heading="11937" respawnTime="60sec" /> <!-- Groz Kropiora -->
			<npc id="24305" x="90152" y="216584" z="-3684" heading="35201" respawnTime="60sec" /> <!-- Groz Krotania -->
			<npc id="24306" x="90120" y="216456" z="-3700" heading="46780" respawnTime="60sec" /> <!-- Groz Krophy -->
			<npc id="24307" x="90328" y="216392" z="-3714" heading="62870" respawnTime="60sec" /> <!-- Groz Krotany -->
			<npc id="24308" x="90440" y="216504" z="-3700" heading="8100" respawnTime="60sec" /> <!-- Water Drake -->
			<npc id="24304" x="88904" y="210488" z="-3693" heading="25891" respawnTime="60sec" /> <!-- Groz Kropiora -->
			<npc id="24305" x="88872" y="210632" z="-3709" heading="19027" respawnTime="60sec" /> <!-- Groz Krotania -->
			<npc id="24306" x="88984" y="210664" z="-3724" heading="2555" respawnTime="60sec" /> <!-- Groz Krophy -->
			<npc id="24307" x="89096" y="210584" z="-3718" heading="58779" respawnTime="60sec" /> <!-- Groz Krotany -->
			<npc id="24308" x="89080" y="210424" z="-3688" heading="48072" respawnTime="60sec" /> <!-- Water Drake -->
			<npc id="24304" x="87896" y="212120" z="-3639" heading="29966" respawnTime="60sec" /> <!-- Groz Kropiora -->
			<npc id="24305" x="87976" y="212216" z="-3631" heading="9770" respawnTime="60sec" /> <!-- Groz Krotania -->
			<npc id="24306" x="88184" y="212168" z="-3594" heading="3781" respawnTime="60sec" /> <!-- Groz Krophy -->
			<npc id="24307" x="88152" y="212008" z="-3611" heading="46501" respawnTime="60sec" /> <!-- Groz Krotany -->
			<npc id="24308" x="87960" y="211912" z="-3633" heading="37671" respawnTime="60sec" /> <!-- Water Drake -->
		</group>
	</spawn>
</list>
