<?xml version="1.0" encoding="UTF-8"?>
<list xmlns:xsi="http://www.w3.org/2001/XMLSchema-instance" xsi:noNamespaceSchemaLocation="../../xsd/buylist.xsd">
	<!-- Krishna R110-Grade Weapons (Blessed) -->
	<item id="80133" price="0" />
	<item id="80134" price="0" />
	<item id="80135" price="0" />
	<item id="80136" price="0" />
	<item id="80137" price="0" />
	<item id="80138" price="0" />
	<item id="80139" price="0" />
	<item id="80140" price="0" />
	<item id="80141" price="0" />
	<item id="80142" price="0" />
	<item id="80143" price="0" />
	<item id="80144" price="0" />
	<item id="80145" price="0" />
	<item id="80146" price="0" />
</list>
