<?xml version="1.0" encoding="UTF-8"?>
<list xmlns:xsi="http://www.w3.org/2001/XMLSchema-instance" xsi:noNamespaceSchemaLocation="../../xsd/buylist.xsd">
	<!-- Awakening R-Grade Bracelets -->
	<item id="17360" price="0" />
	<item id="19449" price="0" />
	<item id="19455" price="0" />
	<item id="19461" price="0" />
	<item id="19471" price="0" />
	<item id="19474" price="0" />
	<item id="19477" price="0" />
	<item id="19480" price="0" />
	<item id="34859" price="0" />
	<item id="34860" price="0" />
	<item id="35293" price="0" />
	<item id="35294" price="0" />
	<item id="38565" price="0" />
	<item id="38566" price="0" />
	<item id="38567" price="0" />
	<item id="38568" price="0" />
	<item id="38569" price="0" />
	<item id="38570" price="0" />
	<item id="47505" price="0" />
	<item id="47506" price="0" />
	<item id="47507" price="0" />
	<item id="47508" price="0" />
	<item id="47509" price="0" />
	<item id="47510" price="0" />
	<item id="47740" price="0" />
	<item id="47741" price="0" />
	<item id="47742" price="0" />
	<item id="47743" price="0" />
	<item id="47744" price="0" />
	<item id="47745" price="0" />
	<item id="48277" price="0" /> <!-- Balthus Kgniht -->
</list>
